geniescript/__init__.py
geniescript/cli.py
geniescript/completion.py
geniescript/instructions.py
geniescript/run.py
geniescript/util.py
geniescript-0.1.1.dist-info/LICENSE
geniescript-0.1.1.dist-info/METADATA
geniescript-0.1.1.dist-info/WHEEL
geniescript-0.1.1.dist-info/entry_points.txt
geniescript-0.1.1.dist-info/RECORD
