Metadata-Version: 2.1
Name: geniescript
Version: 0.1.1
Summary: A Python package for generating and executing data processing scripts using AI language models
Home-page: https://github.com/magland/geniescript
License: Apache-2.0
Keywords: ai,llm,data-processing,scientific-computing,research-tools,code-generation
Author: Jeremy Magland
Author-email: jmagland@flatironinstitute.org
Requires-Python: >=3.9,<4.0
Classifier: Development Status :: 4 - Beta
Classifier: Environment :: Console
Classifier: Intended Audience :: Information Technology
Classifier: Intended Audience :: Science/Research
Classifier: License :: OSI Approved :: Apache Software License
Classifier: Programming Language :: Python :: 3
Classifier: Programming Language :: Python :: 3.9
Classifier: Programming Language :: Python :: 3.10
Classifier: Programming Language :: Python :: 3.11
Classifier: Programming Language :: Python :: 3.12
Classifier: Topic :: Scientific/Engineering
Classifier: Topic :: Scientific/Engineering :: Information Analysis
Requires-Dist: click (>=8.0.0,<9.0.0)
Requires-Dist: openai (>=1.0.0,<2.0.0)
Project-URL: Repository, https://github.com/magland/geniescript
